travis_ci_pypi_deploy_test.py
travis_ci_pypi_deploy_test-0.1.dist-info/DESCRIPTION.rst
travis_ci_pypi_deploy_test-0.1.dist-info/METADATA
travis_ci_pypi_deploy_test-0.1.dist-info/RECORD
travis_ci_pypi_deploy_test-0.1.dist-info/WHEEL
travis_ci_pypi_deploy_test-0.1.dist-info/metadata.json
travis_ci_pypi_deploy_test-0.1.dist-info/top_level.txt
