Metadata-Version: 2.0
Name: travis-ci-pypi-deploy-test
Version: 0.1
Summary: A Python package to test the Travis-CI PyPI deploy.
Home-page: https://github.com/jezdez/travis-ci-pypi-deploy-test
Author: Jannis Leidel
Author-email: jannis@leidel.info
License: MIT license
Platform: UNKNOWN
